<?xml version="1.0"?>
<opencv_storage>
<stage6>
  <maxWeakCount>12</maxWeakCount>
  <stageThreshold>-1.4138222932815552e+00</stageThreshold>
  <weakClassifiers>
    <_>
      <internalNodes>
        0 -1 33260 -504368934 1795121406 317879027 2011003771 -201326600
        -105137030 -151224581 871576315</internalNodes>
      <leafValues>
        -3.1534570455551147e-01 5.3617018461227417e-01</leafValues></_>
    <_>
      <internalNodes>
        0 -1 48751 919809471 929290803 -1213513921 2075815922 868159887
        972504959 -855696129 -4730945</internalNodes>
      <leafValues>
        -3.1279966235160828e-01 5.3266751766204834e-01</leafValues></_>
    <_>
      <internalNodes>
        0 -1 40672 -1255170185 -490143825 1073736939 -1159010782
        -268599721 166723551 -84176 -169345242</internalNodes>
      <leafValues>
        -3.5898086428642273e-01 4.7710368037223816e-01</leafValues></_>
    <_>
      <internalNodes>
        0 -1 78384 -69490305 531294559 -1970181582 -1336747910 580644878
        -854996473 -859021216 -463406752</internalNodes>
      <leafValues>
        -4.2227929830551147e-01 3.8967177271842957e-01</leafValues></_>
    <_>
      <internalNodes>
        0 -1 70967 -268450025 119798575 -1376887362 -1989689365
        1786202005 -847456257 -386080308 -1464343553</internalNodes>
      <leafValues>
        -3.8814684748649597e-01 4.2948159575462341e-01</leafValues></_>
    <_>
      <internalNodes>
        0 -1 78107 -286261411 -29922649 -320144774 2055075491
        -1939395004 -1892450314 -235082340 -218890497</internalNodes>
      <leafValues>
        -3.4143894910812378e-01 4.7980189323425293e-01</leafValues></_>
    <_>
      <internalNodes>
        0 -1 18588 1516093627 322884027 -1853877229 -1664941997
        1488587109 236704154 135383156 -627320264</internalNodes>
      <leafValues>
        -4.2354553937911987e-01 4.1273945569992065e-01</leafValues></_>
    <_>
      <internalNodes>
        0 -1 80635 -1184642497 2145447669 -42012053 -828654241
        -1074397699 -1359585411 -1767444666 1798815574</internalNodes>
      <leafValues>
        -3.4779533743858337e-01 5.0439125299453735e-01</leafValues></_>
    <_>
      <internalNodes>
        0 -1 73530 -358896833 781458819 -796668998 685769419 1300833543
        995478328 -465106306 -1496056829</internalNodes>
      <leafValues>
        -4.4235935807228088e-01 4.0418693423271179e-01</leafValues></_>
    <_>
      <internalNodes>
        0 -1 43225 -460442159 403073456 -1072918057 1040474243 177670545
        -41496572 -1450690268 -1361828508</internalNodes>
      <leafValues>
        -4.6187284588813782e-01 3.9558804035186768e-01</leafValues></_>
    <_>
      <internalNodes>
        0 -1 45792 -958630509 -979185398 -1818420814 -525709084
        -319307431 -1144340248 -1784977068 -1982729376</internalNodes>
      <leafValues>
        -4.1297069191932678e-01 4.2646959424018860e-01</leafValues></_>
    <_>
      <internalNodes>
        0 -1 63526 211560045 480191120 537445853 -1407673904 -2003224392
        -744816511 1019363919 -1230585052</internalNodes>
      <leafValues>
        -5.8972221612930298e-01 3.0974829196929932e-01</leafValues></_></weakClassifiers></stage6>
</opencv_storage>
