<?xml version="1.0"?>
<opencv_storage>
<stage8>
  <maxWeakCount>12</maxWeakCount>
  <stageThreshold>-8.8754725456237793e-01</stageThreshold>
  <weakClassifiers>
    <_>
      <internalNodes>
        0 -1 212510 2136948287 1030568703 -324363 -1145438337 1022696874
        779370232 -54595 -4196353</internalNodes>
      <leafValues>
        -1.3692407310009003e-01 6.4675325155258179e-01</leafValues></_>
    <_>
      <internalNodes>
        0 -1 47923 -202906750 -142121622 59342719 -983246978 -1823673176
        -157759080 -473460685 -531499194</internalNodes>
      <leafValues>
        -4.3884128332138062e-01 3.7519797682762146e-01</leafValues></_>
    <_>
      <internalNodes>
        0 -1 484874 201944903 -208338473 1080103303 -271060533
        1222087630 -127891325 541311022 1691329544</internalNodes>
      <leafValues>
        -4.3671172857284546e-01 3.5539385676383972e-01</leafValues></_>
    <_>
      <internalNodes>
        0 -1 100239 1742602086 1368623177 278726035 1675610329
        1457243551 490225959 1933726299 1830784415</internalNodes>
      <leafValues>
        -4.9737331271171570e-01 3.0489194393157959e-01</leafValues></_>
    <_>
      <internalNodes>
        0 -1 392329 -1094538243 894582982 -1874454735 771888256
        566298030 260686025 -1676998997 -1679385946</internalNodes>
      <leafValues>
        -3.9638558030128479e-01 3.6786183714866638e-01</leafValues></_>
    <_>
      <internalNodes>
        0 -1 289706 -1031609568 -805027741 304212743 -1111376984
        1696100605 -1160738546 -128842581 272974658</internalNodes>
      <leafValues>
        -5.0603520870208740e-01 2.7989059686660767e-01</leafValues></_>
    <_>
      <internalNodes>
        0 -1 302217 -75252310 981729301 688921006 -635956932 -2013126200
        8408257 1116316392 1037583307</internalNodes>
      <leafValues>
        -4.2982566356658936e-01 3.6964595317840576e-01</leafValues></_>
    <_>
      <internalNodes>
        0 -1 518316 1743117883 -8913097 2130046955 -270172441 -302076497
        -294127634 -453120466 -1679301850</internalNodes>
      <leafValues>
        -2.7807736396789551e-01 5.8109557628631592e-01</leafValues></_>
    <_>
      <internalNodes>
        0 -1 100812 -69207269 327721091 1090617372 -2130542591 847853947
        -1089453766 197150 -366546097</internalNodes>
      <leafValues>
        -3.4146091341972351e-01 4.3430647253990173e-01</leafValues></_>
    <_>
      <internalNodes>
        0 -1 300274 246918878 1062344980 1350611281 226890178 1210417160
        1016894100 621355529 1541076520</internalNodes>
      <leafValues>
        -5.6739628314971924e-01 2.7505937218666077e-01</leafValues></_>
    <_>
      <internalNodes>
        0 -1 195599 -1589177531 596565677 -17896277 1876504311
        1039828761 -1665303044 1700182638 184227627</internalNodes>
      <leafValues>
        -3.8229328393936157e-01 4.2564788460731506e-01</leafValues></_>
    <_>
      <internalNodes>
        0 -1 317270 -1043871961 113393665 1028205607 -595361256
        1660949875 72781965 1473214227 -152118693</internalNodes>
      <leafValues>
        -4.5144343376159668e-01 3.5515344142913818e-01</leafValues></_></weakClassifiers></stage8>
</opencv_storage>
